python_rebase/__init__.py
python_rebase/api_response.py
python_rebase/mismatched_articulations_error.py
python_rebase/missing_attribute_error.py
python_rebase/movement.py
python_rebase/rebase_client.py
python_rebase/register.py
python_rebase/repeated_articulation_error.py
python_rebase/rotation.py
python_rebase/session.py
python_rebase/unauthorized_user_error.py
python_rebase/util.py
python_rebase-0.3.4.dist-info/METADATA
python_rebase-0.3.4.dist-info/WHEEL
python_rebase-0.3.4.dist-info/licenses/LICENSE
python_rebase-0.3.4.dist-info/RECORD
