Metadata-Version: 2.3
Name: python-rebase
Version: 0.3.4
Summary: Python implementation of the ReBase API
Project-URL: Repository, https://github.com/MrTrotta2010/python-rebase
Project-URL: Changelog, https://github.com/MrTrotta2010/python-rebase/blob/main/CHANGELOG.md
Author-email: Tiago Trotta <mrtrotta2010@gmail.com>
License-File: LICENSE
Keywords: database,databases,gesture tracking,medical,movement tracking
Classifier: Development Status :: 4 - Beta
Classifier: Intended Audience :: Healthcare Industry
Classifier: License :: OSI Approved :: GNU General Public License v3 or later (GPLv3+)
Classifier: Operating System :: OS Independent
Classifier: Programming Language :: Python :: 3.10
Classifier: Topic :: Scientific/Engineering :: Medical Science Apps.
Classifier: Topic :: Software Development :: Libraries :: Python Modules
Requires-Python: >=3.10
Requires-Dist: requests
